zuulcilint/__init__.py
zuulcilint/__main__.py
zuulcilint/checker.py
zuulcilint/utils.py
zuulcilint/zuul-schema.json
zuulcilint-1.0.0.dist-info/LICENSE
zuulcilint-1.0.0.dist-info/METADATA
zuulcilint-1.0.0.dist-info/WHEEL
zuulcilint-1.0.0.dist-info/entry_points.txt
zuulcilint-1.0.0.dist-info/RECORD
