Metadata-Version: 2.3
Name: zuulcilint
Version: 1.0.0
Summary: Zuul CI linter
Home-page: https://github.com/codesquadnest/zuulcilint
License: MIT
Keywords: zuul,ci,linter
Author: Pedro Baptista
Author-email: pedro.miguel.baptista@gmail.com
Requires-Python: >=3.9,<4.0
Classifier: License :: OSI Approved :: MIT License
Classifier: Programming Language :: Python :: 3
Classifier: Programming Language :: Python :: 3.9
Classifier: Programming Language :: Python :: 3.10
Classifier: Programming Language :: Python :: 3.11
Classifier: Programming Language :: Python :: 3.12
Classifier: Programming Language :: Python :: 3.13
Requires-Dist: PyYAML (>=6.0.1,<7.0.0)
Requires-Dist: jsonschema (>=4.23.0,<5.0.0)
Requires-Dist: poetry (>=2.0.0,<3.0.0)
Requires-Dist: six (>=1.16.0,<2.0.0)
Project-URL: Repository, https://github.com/codesquadnest/zuulcilint
